mailiness/__init__.py
mailiness/cli.py
mailiness/commands.py
mailiness/dkim.py
mailiness/handlers.py
mailiness/repo.py
mailiness/settings.py
mailiness-0.2.3.dist-info/METADATA
mailiness-0.2.3.dist-info/WHEEL
mailiness-0.2.3.dist-info/entry_points.txt
mailiness-0.2.3.dist-info/licenses/LICENSE
mailiness-0.2.3.dist-info/RECORD
